fotokilof/__init__.py
fotokilof/__main__.py
fotokilof/check_new_version.py
fotokilof/common.py
fotokilof/convert.py
fotokilof/convert_common.py
fotokilof/convert_pillow.py
fotokilof/convert_wand.py
fotokilof/entries.py
fotokilof/gui.py
fotokilof/gui_bindings.py
fotokilof/gui_tooltips.py
fotokilof/ini_read.py
fotokilof/ini_save.py
fotokilof/magick.py
fotokilof/test_modules.py
fotokilof/version.py
fotokilof/locale/bg/LC_MESSAGES/fotokilof.mo
fotokilof/locale/de/LC_MESSAGES/fotokilof.mo
fotokilof/locale/en/LC_MESSAGES/fotokilof.mo
fotokilof/locale/id/LC_MESSAGES/fotokilof.mo
fotokilof/locale/it/LC_MESSAGES/fotokilof.mo
fotokilof/locale/pl/LC_MESSAGES/fotokilof.mo
fotokilof/locale/tr/LC_MESSAGES/fotokilof.mo
fotokilof-5.2.3.dist-info/licenses/LICENSE
fotokilof-5.2.3.dist-info/METADATA
fotokilof-5.2.3.dist-info/WHEEL
fotokilof-5.2.3.dist-info/entry_points.txt
fotokilof-5.2.3.dist-info/top_level.txt
fotokilof-5.2.3.dist-info/RECORD
