Metadata-Version: 2.4
Name: FotoKilof
Version: 5.2.3
Summary: Nice gui for ImageMagick and Pillow
Author-email: Tomasz Łuczak <tlu@team-tl.pl>
License-Expression: MIT
Project-URL: Source, https://github.com/TeaM-TL/FotoKilof/
Project-URL: Tracker, https://github.com/TeaM-TL/FotoKilof/issues/
Classifier: Development Status :: 5 - Production/Stable
Classifier: Programming Language :: Python
Classifier: Programming Language :: Python :: 3.10
Classifier: Programming Language :: Python :: 3.11
Classifier: Programming Language :: Python :: 3.12
Classifier: Programming Language :: Python :: 3.13
Classifier: Operating System :: MacOS
Classifier: Operating System :: Microsoft :: Windows
Classifier: Operating System :: Unix
Requires-Python: >=3.10
License-File: LICENSE
Requires-Dist: darkdetect
Requires-Dist: FindSystemFontsFilename
Requires-Dist: pillow
Requires-Dist: pywin32; platform_system == "Windows"
Requires-Dist: pyperclipimg; platform_system == "Linux" or platform_system == "Darwin" or platform_system == "Windows"
Requires-Dist: requests
Requires-Dist: ttkbootstrap>=1.18.0
Requires-Dist: wand
Dynamic: license-file
